{
  "type": "magforest:alchemical",
  "ingredients": [
    {
      "item": "minecraft:air"
    },
    {
      "item": "magforest:crystal_phial"
    },
    {
      "item": "minecraft:honey_bottle"
    },
    {
      "item": "magforest:hyacinth"
    },
    {
      "item": "minecraft:oxeye_daisy"
    },
    {
      "item": "minecraft:air"
    },
    {
      "item": "minecraft:air"
    },
    {
      "item": "minecraft:air"
    },
    {
      "item": "minecraft:air"
    }
  ],
  "output": {
    "item": "magforest:potion_healing",
    "count": 3
  }
}